numlookupapi/__init__.py
numlookupapi/client.py
numlookupapi-0.1.dist-info/METADATA
numlookupapi-0.1.dist-info/WHEEL
numlookupapi-0.1.dist-info/top_level.txt
numlookupapi-0.1.dist-info/RECORD
